cjm_tqdm_capture/__init__.py
cjm_tqdm_capture/_modidx.py
cjm_tqdm_capture/job_runner.py
cjm_tqdm_capture/patch_tqdm.py
cjm_tqdm_capture/progress_info.py
cjm_tqdm_capture/progress_monitor.py
cjm_tqdm_capture/streaming.py
cjm_tqdm_capture-0.0.6.dist-info/licenses/LICENSE
cjm_tqdm_capture-0.0.6.dist-info/METADATA
cjm_tqdm_capture-0.0.6.dist-info/WHEEL
cjm_tqdm_capture-0.0.6.dist-info/entry_points.txt
cjm_tqdm_capture-0.0.6.dist-info/top_level.txt
cjm_tqdm_capture-0.0.6.dist-info/RECORD
